sfchecks/__init__.py
sfchecks/logger.py
sfchecks/types.py
sfchecks/utils.py
sfchecks/tools/__init__.py
sfchecks/tools/command/__init__.py
sfchecks/tools/file/__init__.py
sfchecks/tools/privileges/__init__.py
sfchecks-1.6.5.dist-info/licenses/LICENSE
sfchecks-1.6.5.dist-info/METADATA
sfchecks-1.6.5.dist-info/WHEEL
sfchecks-1.6.5.dist-info/top_level.txt
sfchecks-1.6.5.dist-info/RECORD
