Metadata-Version: 2.4
Name: sfchecks
Version: 1.6.5
Summary: A library for writing checks for SecureFlag's hands-on secure coding training labs
License-File: LICENSE
Requires-Dist: loguru==0.7.2
Provides-Extra: dev
Requires-Dist: pytest==8.2.2; extra == "dev"
Requires-Dist: pdoc==15.0.1; extra == "dev"
Requires-Dist: black==24.4.2; extra == "dev"
Dynamic: license-file
